yh_mcp_server_demo/__init__.py
yh_mcp_server_demo-0.1.0.dist-info/WHEEL
yh_mcp_server_demo-0.1.0.dist-info/entry_points.txt
yh_mcp_server_demo-0.1.0.dist-info/METADATA
yh_mcp_server_demo-0.1.0.dist-info/RECORD
