Metadata-Version: 2.3
Name: yh-mcp-server-demo
Version: 0.1.0
Summary: Add your description here
Author: zhouyanghong
Author-email: zhouyanghong <zhouyanghong@qfang.com>
Requires-Dist: mcp[cli]>=1.25.0
Requires-Python: >=3.14
